csbprivatetest/__init__.py
csbprivatetest/datalogger_examples.py
csbprivatetest/georeference.py
csbprivatetest/test.py
csbprivatetest/uncertainty.py
csbprivatetest-0.1.3.dist-info/LICENSE
csbprivatetest-0.1.3.dist-info/METADATA
csbprivatetest-0.1.3.dist-info/WHEEL
csbprivatetest-0.1.3.dist-info/top_level.txt
csbprivatetest-0.1.3.dist-info/RECORD
