Metadata-Version: 2.1
Name: csbprivatetest
Version: 0.1.3
Summary: CSB Toolkit for Georeferencing and Uncertainty Calculations
Home-page: https://github.com/vishwabarathy-cidco/csbprivate
Author: Vishwa Barathy
Author-email: vishwa.barathy@cidco.ca
License: MIT
Platform: UNKNOWN
Classifier: Programming Language :: Python :: 3
Classifier: License :: OSI Approved :: MIT License
Classifier: Operating System :: OS Independent
Requires-Python: >=3.6
